{"author":"Walfun","content_warnings":[],"created_at":"2022-08-14T11:35:53.046856","dev_state":null,"donate_url":null,"downloads":1190,"forum_url":null,"forums":null,"game_support":[{"confidence":11,"game":{"author":"Minetest","name":"minetest_game","release":29742,"short_description":"The classic \"Minetest\". A lightweight and well-maintained base for modding","thumbnail":"https://content.luanti.org/thumbnails/1/8ffd1409ff.png","title":"Minetest Game","type":"game"},"supports":true}],"issue_tracker":null,"license":"MIT","long_description":"# Introduction\n\n**Hello Minetest user, are you looking for a texture pack that changes the default + and X crosshair to a square shaped?\nWell lucky for you, becuase I made a texture pack that replaces the + and X crosshair to the outline square crosshair.\nI hope you enjoy my very first texture pack.<br>\n**-Walfun\n\n# Changelogs\n\n- v0.1: Release.<br>\n- v0.2: Change the description a bit and is now compatible with GreenXenthin's [Mobile Crosshair](https://content.minetest.net/packages/GreenXenith/mobile_crosshair/) mod.","maintainers":["Walfun"],"media_license":"MIT","name":"outline_square_crosshair","provides":[],"release":13436,"repo":null,"score":12.5,"screenshots":["https://content.luanti.org/uploads/e9a1d00908.png","https://content.luanti.org/uploads/3ec49271c0.png","https://content.luanti.org/uploads/30e99899a7.png","https://content.luanti.org/uploads/2dcec70b6e.png"],"short_description":"It replaces the + and X crosshair to the outline square crosshair.","state":"APPROVED","tags":["hud"],"thumbnail":"https://content.luanti.org/thumbnails/1/e9a1d00908.png","title":"Outline Square Crosshair","translation_url":null,"type":"txp","url":"https://content.luanti.org/packages/Walfun/outline_square_crosshair/releases/13436/download/","video_thumbnail_url":null,"video_url":null,"website":null,"dependencies":{"Walfun/outline_square_crosshair":[]},"hash":"0pjvd27phdpf6ml8n46bxz2ppf6hg3fqbpw5avd8vy5csy2yphwn"}