{"author":"Winter94","content_warnings":[],"created_at":"2020-04-04T11:39:50.029072","dev_state":"AS_IS","donate_url":null,"downloads":1364,"forum_url":null,"forums":null,"game_support":[{"confidence":1,"game":{"author":"Warr1024","name":"nodecore_alpha","release":29712,"short_description":"Early-access edition of NodeCore with latest features (and maybe bugs)","thumbnail":"https://content.luanti.org/thumbnails/1/db1a942e1a.png","title":"NodeCore ALPHA","type":"game"},"supports":true},{"confidence":1,"game":{"author":"Warr1024","name":"nodecore","release":29711,"short_description":"Discover and invent in a surreal, unsympathetic world of cubes, patterns, and abstractions.","thumbnail":"https://content.luanti.org/thumbnails/1/8078c595ae.png","title":"NodeCore","type":"game"},"supports":true}],"issue_tracker":"https://github.com/wintersknight94/NC-Lignite/issues/new/choose/","license":"GPL-3.0-only","long_description":"Adds Lignite, an ore of coal, to NodeCore. Burning wood is no longer the only way to get fuel.\n Now outdated, please use NodeCore Coal instead. \nhttps://content.minetest.net/packages/Winter94/wc_coal/\n\nThank you,      \n\n\t\t\t\t\t--Winter94 (WintersKnight) (WintersKnight94)","maintainers":["Winter94"],"media_license":"GPL-3.0-only","name":"nc_lignite","provides":["nc_lignite"],"release":10327,"repo":"https://github.com/wintersknight94/NC-Lignite","score":2.4,"screenshots":["https://content.luanti.org/uploads/EwRBLcDf4R.png"],"short_description":"Adds Lignite, an ore of coal. Now outdated, please use NodeCore Coal instead. See Below.","state":"APPROVED","tags":["environment","mapgen","survival"],"thumbnail":"https://content.luanti.org/thumbnails/1/EwRBLcDf4R.png","title":"NodeCore Lignite","translation_url":null,"type":"mod","url":"https://content.luanti.org/packages/Winter94/nc_lignite/releases/10327/download/","video_thumbnail_url":null,"video_url":null,"website":null,"dependencies":{"Winter94/nc_lignite":[{"is_optional":false,"name":"nc_items","packages":["Warr1024/nodecore","Warr1024/nodecore_alpha"]},{"is_optional":false,"name":"nc_lode","packages":["Warr1024/nodecore","Warr1024/nodecore_alpha"]},{"is_optional":false,"name":"nc_terrain","packages":["Warr1024/nodecore","Warr1024/nodecore_alpha"]},{"is_optional":false,"name":"nc_api_all","packages":["Warr1024/nodecore","Warr1024/nodecore_alpha"]}]},"hash":"1iq7bh6y37c8fs2snnis3kj39zhwihdavs8fswxi1s4w6v1iwwvj"}