{
  "author": "Goops",
  "content_warnings": [],
  "created_at": "2022-03-07T12:11:18.204709",
  "dev_state": null,
  "donate_url": null,
  "downloads": 1143,
  "forum_url": "https://forum.luanti.org/viewtopic.php?t=28313",
  "forums": 28313,
  "game_support": [
    {
      "confidence": 1,
      "game": {
        "author": "MeseCraft",
        "name": "mesecraft",
        "release": 29792,
        "short_description": "Work in Progress. The best game for Minetest. A survival game with new depth, mechanics, biomes, mobs and many essential additions. Has a focus on being fun, user-friendly, stable, and minimalist but featured.",
        "thumbnail": "https://content.luanti.org/thumbnails/1/bd43210a7e.png",
        "title": "MeseCraft",
        "type": "game"
      },
      "supports": true
    },
    {
      "confidence": 1,
      "game": {
        "author": "1248",
        "name": "regnum",
        "release": 28584,
        "short_description": "Fight monsters, collect XP, craft battleaxes, armor, guns and lots more.",
        "thumbnail": "https://content.luanti.org/thumbnails/1/3EqCRnJzzv.png",
        "title": "Regnum",
        "type": "game"
      },
      "supports": true
    },
    {
      "confidence": 1,
      "game": {
        "author": "hilol",
        "name": "epic_combat",
        "release": 27975,
        "short_description": "Fight your enemies with various weapons and protect yourself with distinct sets of Armour, whilst sharpening your skills in PVP and PVE.",
        "thumbnail": "https://content.luanti.org/thumbnails/1/a0b633cedd.png",
        "title": "Epic Combat",
        "type": "game"
      },
      "supports": true
    },
    {
      "confidence": 1,
      "game": {
        "author": "Minetest",
        "name": "minetest_game",
        "release": 29742,
        "short_description": "The classic \"Minetest\". A lightweight and well-maintained base for modding",
        "thumbnail": "https://content.luanti.org/thumbnails/1/8ffd1409ff.png",
        "title": "Minetest Game",
        "type": "game"
      },
      "supports": true
    },
    {
      "confidence": 1,
      "game": {
        "author": "Kimapr",
        "name": "nonsensical_skyblock",
        "release": 27427,
        "short_description": "skyblock game BASED on crafting. no quest cringe! bonemeal go brrrr",
        "thumbnail": "https://content.luanti.org/thumbnails/1/2f8309e348.png",
        "title": "Nonsensical Skyblock",
        "type": "game"
      },
      "supports": true
    },
    {
      "confidence": 1,
      "game": {
        "author": "1248",
        "name": "regnum2",
        "release": 28585,
        "short_description": "This is the second part of Regnum",
        "thumbnail": "https://content.luanti.org/thumbnails/1/Hmlddw7prL.png",
        "title": "Regnum 2",
        "type": "game"
      },
      "supports": true
    },
    {
      "confidence": 1,
      "game": {
        "author": "BuckarooBanzay",
        "name": "mesecons_lab",
        "release": 27246,
        "short_description": "Work in Progress. Mesecons laboratory and tutorials",
        "thumbnail": "https://content.luanti.org/thumbnails/1/NKSVMnvh05.png",
        "title": "Mesecons lab",
        "type": "game"
      },
      "supports": true
    },
    {
      "confidence": 1,
      "game": {
        "aliases": [
          "VanessaE/dreambuilder_game"
        ],
        "author": "mt-mods",
        "name": "dreambuilder_game",
        "release": 29790,
        "short_description": "Dreambuilder is my attempt to give the player pretty much everything they could ever want to build with, and all the tools they should need to actually get the job done.",
        "thumbnail": "https://content.luanti.org/thumbnails/1/881d766d45.png",
        "title": "Dreambuilder Game",
        "type": "game"
      },
      "supports": true
    }
  ],
  "issue_tracker": "https://github.com/MT-Goops/rings/issues/new/choose/",
  "license": "CC-BY-SA-4.0",
  "long_description": "Minetest mod that adds rings with temporary player effects\n\n* _Celestial Ring_ : allows to fly\n\n* _Infernal Ring_ : gives fire resistance\n\n* _Abyssal Ring_ : gives water resistance\n\n* _Hardening Ring_ : gives Iron Fist (via Activation Ring)\n\n* _Enlightning Ring_ : makes player shine\n\n* _Activation Ring_ : provides control of the rings:\n    - activates/desactivates the rings (primary/secondary usage) ;\n    - applies special effects (cf. Iron Fist) ;\n    - in sneak mode: toggles automatic activation/toggles hud (primary/secondary usage).\n\n* _Random Ring_ : drops a random ring\n\nGlooptest mod dependency was made optional by including part of its code.",
  "maintainers": [
    "Goops"
  ],
  "media_license": "CC-BY-SA-4.0",
  "name": "goops_rings",
  "provides": [
    "goops_rings"
  ],
  "release": 12806,
  "repo": "https://github.com/MT-Goops/rings",
  "score": 157.7,
  "screenshots": [
    "https://content.luanti.org/uploads/fc7145d588.png",
    "https://content.luanti.org/uploads/5c52b89e7f.png",
    "https://content.luanti.org/uploads/3196724cc9.png",
    "https://content.luanti.org/uploads/368766a9b0.png"
  ],
  "short_description": "Add rings with temporary player effects",
  "state": "APPROVED",
  "tags": [
    "player_effects"
  ],
  "thumbnail": "https://content.luanti.org/thumbnails/1/fc7145d588.png",
  "title": "Rings",
  "translation_url": null,
  "type": "mod",
  "url": "https://content.luanti.org/packages/Goops/goops_rings/releases/12806/download/",
  "video_thumbnail_url": null,
  "video_url": null,
  "website": null,
  "dependencies": {
    "Calinou/moreores": [],
    "Goops/goops_rings": [
      {
        "is_optional": false,
        "name": "3d_armor",
        "packages": [
          "Noodlemire/voxeldungeon",
          "1248/regnum",
          "1248/regnum2",
          "stu/3d_armor",
          "bell07/whynot_game",
          "Kimapr/nonsensical_skyblock",
          "MeseCraft/mesecraft",
          "rlars/occupymoon_game",
          "PetiAPocok/minetest_extended",
          "hilol/epic_combat",
          "Astrobe/minefall",
          "EmptyStar/asuna"
        ]
      },
      {
        "is_optional": false,
        "name": "moreores",
        "packages": [
          "BuckarooBanzay/mesecons_lab",
          "1248/regnum",
          "1248/regnum2",
          "Calinou/moreores",
          "Kimapr/nonsensical_skyblock",
          "MeseCraft/mesecraft",
          "hilol/epic_combat",
          "mt-mods/dreambuilder_game"
        ]
      },
      {
        "is_optional": false,
        "name": "default",
        "packages": [
          "AiTechEye/xaenvironment",
          "Hi_World/newplanet",
          "Noodlemire/voxeldungeon",
          "JALdMIC/survivethedays",
          "sunnysideup/holidayhorrors",
          "BuckarooBanzay/mesecons_lab",
          "nam/porko",
          "Amaz/lordofthetest",
          "1248/castrum",
          "Thunder1035/etb",
          "1248/regnum",
          "Minetest/minetest_game",
          "debiankaios/proxima_survival",
          "carlos_rupp/berzerkpt",
          "1248/regnum2",
          "miroptics/qiskitblocks_miro",
          "KareaGhandTrail/block_assault_mapmaker",
          "KareaGhandTrail/block_assault",
          "Casimir/voxelgarden",
          "bell07/whynot_game",
          "JavaFXpert/qiskitblocks",
          "Kimapr/nonsensical_skyblock",
          "jgordon510/gridlocks",
          "giga-turbo/codecube",
          "niwla23/runorfall",
          "Thunder1035/pacman",
          "Big_Caballito/no_mans_land",
          "MeseCraft/mesecraft",
          "hilol/epic_combat",
          "TheFanne/raining_nodes",
          "rlars/occupymoon_game",
          "PetiAPocok/minetest_extended",
          "mooD_Slayer/ksurvive",
          "EmptyStar/asuna",
          "mt-mods/dreambuilder_game",
          "rubenwardy/capturetheflag"
        ]
      }
    ],
    "stu/3d_armor": [
      {
        "is_optional": false,
        "name": "default",
        "packages": [
          "AiTechEye/xaenvironment",
          "Hi_World/newplanet",
          "Noodlemire/voxeldungeon",
          "JALdMIC/survivethedays",
          "sunnysideup/holidayhorrors",
          "BuckarooBanzay/mesecons_lab",
          "nam/porko",
          "Amaz/lordofthetest",
          "1248/castrum",
          "Thunder1035/etb",
          "1248/regnum",
          "Minetest/minetest_game",
          "debiankaios/proxima_survival",
          "carlos_rupp/berzerkpt",
          "1248/regnum2",
          "miroptics/qiskitblocks_miro",
          "KareaGhandTrail/block_assault_mapmaker",
          "KareaGhandTrail/block_assault",
          "Casimir/voxelgarden",
          "bell07/whynot_game",
          "JavaFXpert/qiskitblocks",
          "Kimapr/nonsensical_skyblock",
          "jgordon510/gridlocks",
          "giga-turbo/codecube",
          "niwla23/runorfall",
          "Thunder1035/pacman",
          "Big_Caballito/no_mans_land",
          "MeseCraft/mesecraft",
          "hilol/epic_combat",
          "TheFanne/raining_nodes",
          "rlars/occupymoon_game",
          "PetiAPocok/minetest_extended",
          "mooD_Slayer/ksurvive",
          "EmptyStar/asuna",
          "mt-mods/dreambuilder_game",
          "rubenwardy/capturetheflag"
        ]
      },
      {
        "is_optional": false,
        "name": "player_api",
        "packages": [
          "aerkiaga/nodeverse",
          "Hume2/minesweeper_3d",
          "BuckarooBanzay/mesecons_lab",
          "StarNinjas/jail_escape",
          "Hi_World/newplanet",
          "Noodlemire/voxeldungeon",
          "JALdMIC/survivethedays",
          "sunnysideup/holidayhorrors",
          "mt-mods/driftgame",
          "BRNSystems/blocky_portaling",
          "xenonca/luckysweeper",
          "Wuzzy/lazarr",
          "1248/castrum",
          "Thunder1035/etb",
          "Blockhead/sotm",
          "SuperStarSonic/reentry",
          "Minetest/minetest_game",
          "Hume2/boxworld3d",
          "1248/regnum",
          "debiankaios/proxima_survival",
          "carlos_rupp/berzerkpt",
          "1248/regnum2",
          "miroptics/qiskitblocks_miro",
          "KareaGhandTrail/block_assault_mapmaker",
          "jgordon510/color_block",
          "Lone_Wolf/torrlund",
          "KareaGhandTrail/block_assault",
          "dibesfer/colorlandia",
          "Casimir/voxelgarden",
          "BuckarooBanzay/super_sam",
          "bell07/whynot_game",
          "xenonca/luckydude",
          "Emojiminetest/parkour",
          "Mantar/exile",
          "JavaFXpert/qiskitblocks",
          "Kimapr/nonsensical_skyblock",
          "Wuzzy/repixture",
          "jgordon510/gridlocks",
          "niwla23/runorfall",
          "Thunder1035/pacman",
          "Big_Caballito/no_mans_land",
          "MeseCraft/mesecraft",
          "hilol/epic_combat",
          "jamiebearcub/grand_theft_box",
          "TheFanne/raining_nodes",
          "rlars/occupymoon_game",
          "PetiAPocok/minetest_extended",
          "mooD_Slayer/ksurvive",
          "Astrobe/minefall",
          "mt-mods/dreambuilder_game",
          "EmptyStar/asuna",
          "rubenwardy/capturetheflag"
        ]
      }
    ]
  },
  "hash": "1haqbvdbs5yl24h99k40163p26dd6bmlq92rsqlgz7lwa8cw4zbb"
}
