{
  "author": "KareaGhandTrail",
  "content_warnings": [],
  "created_at": "2024-12-17T18:32:08.669961",
  "dev_state": "ACTIVELY_DEVELOPED",
  "donate_url": null,
  "downloads": 82,
  "forum_url": null,
  "forums": null,
  "game_support": [],
  "issue_tracker": null,
  "license": "LGPL-2.1-only",
  "long_description": "Adds /spawn and /city commands to your server|world.\n\nHow to use:\n\n* /spawn (set): Teleport to spawn or set a place for spawn\n\n* /city (set): Teleport to city or set a place for city **Optional**\n\nHope this help you ^-^",
  "maintainers": [
    "KareaGhandTrail"
  ],
  "media_license": "LGPL-2.1-only",
  "name": "spw",
  "provides": [
    "spw"
  ],
  "release": 28956,
  "repo": null,
  "score": 10.5,
  "screenshots": [
    "https://content.luanti.org/uploads/2799512665.png"
  ],
  "short_description": "Adds /spawn and /city to your world, you can set places ingame without restarting the server",
  "state": "APPROVED",
  "tags": [
    "chat",
    "server_tools"
  ],
  "thumbnail": "https://content.luanti.org/thumbnails/1/2799512665.png",
  "title": "Spawn Command",
  "translation_url": null,
  "type": "mod",
  "url": "https://content.luanti.org/packages/KareaGhandTrail/spw/releases/28956/download/",
  "video_thumbnail_url": null,
  "video_url": null,
  "website": null,
  "dependencies": {
    "KareaGhandTrail/spw": []
  },
  "hash": "13if4yy8kqdp5lwzqy3y849kvrg02rgv6fi6vfv018cjxsgn8vks"
}
