{
  "author": "jgordon510",
  "content_warnings": [],
  "created_at": "2024-10-28T21:58:57.639593",
  "dev_state": "MAINTENANCE_ONLY",
  "donate_url": null,
  "downloads": 385,
  "forum_url": null,
  "forums": null,
  "game_support": [],
  "issue_tracker": null,
  "license": "LGPL-2.1-only",
  "long_description": "This is an escape room puzzle game about programming and art.  \n\nIn order to progress through the rooms, you must line up blocks to create programs to draw pixel art on the wall.\n\nIt starts easy, but gets very hard by the end.  ",
  "maintainers": ["jgordon510"],
  "media_license": "CC-BY-SA-3.0",
  "name": "gridlocks",
  "provides": [
    "boards",
    "butterflies",
    "creative",
    "default",
    "display_api",
    "doors",
    "dye",
    "farming",
    "fireflies",
    "flowers",
    "font_api",
    "font_botic",
    "font_metro",
    "gridlock",
    "gridlock_lab",
    "moreblocks",
    "ontime_clocks",
    "player_api",
    "scifi_nodes",
    "sfinv",
    "signs",
    "signs_api",
    "signs_road",
    "stairs",
    "steles",
    "vessels",
    "wool",
    "xcompat",
    "xpanes"
  ],
  "release": 28415,
  "repo": "https://github.com/jgordon510/minetest_gridlocks",
  "score": 37.5,
  "screenshots": ["https://content.luanti.org/uploads/5cbe6a208b.png"],
  "short_description": "Learn programming, solve puzzles, and make pixelart.  An escape room game.",
  "state": "APPROVED",
  "tags": ["puzzle"],
  "thumbnail": "https://content.luanti.org/thumbnails/1/5cbe6a208b.png",
  "title": "gridlocks",
  "translation_url": null,
  "type": "game",
  "url": "https://content.luanti.org/packages/jgordon510/gridlocks/releases/28415/download/",
  "video_thumbnail_url": null,
  "video_url": null,
  "website": null,
  "dependencies": {
    "jgordon510/gridlocks": []
  },
  "hash": "0vmiclpyn1kfnnnlgm43c41imi5wgafs4jqd8cwzsqqb2hwfgl6y"
}
