{
  "author": "nolombic",
  "content_warnings": [],
  "created_at": "2020-07-04T20:34:30.517772",
  "dev_state": null,
  "donate_url": "https://paypal.me/nolombic",
  "downloads": 2357,
  "forum_url": "https://forum.luanti.org/viewtopic.php?t=25014",
  "forums": 25014,
  "game_support": [
    {
      "confidence": 1,
      "game": {
        "author": "PetiAPocok",
        "name": "minetest_extended",
        "release": 7305,
        "short_description": "The extended version of the default Minetest Game.",
        "thumbnail": "https://content.luanti.org/thumbnails/1/GAjAavITNq.png",
        "title": "Minetest Extended",
        "type": "game"
      },
      "supports": true
    },
    {
      "confidence": 1,
      "game": {
        "author": "rubenwardy",
        "name": "capturetheflag",
        "release": 30017,
        "short_description": "Two or more teams battle to snatch and return the enemy flags, before the enemy takes their own!",
        "thumbnail": "https://content.luanti.org/thumbnails/1/67c591b9b8.png",
        "title": "Capture the Flag",
        "type": "game"
      },
      "supports": true
    },
    {
      "confidence": 1,
      "game": {
        "author": "miroptics",
        "name": "qiskitblocks_miro",
        "release": 26302,
        "short_description": "Work in Progress. Fork of JavaFXpert/QiskitBlocks - Game that teaches quantum computing",
        "thumbnail": "https://content.luanti.org/thumbnails/1/f34178cf2b.png",
        "title": "QuantumBuilder - a QiskitBlocks fork",
        "type": "game"
      },
      "supports": true
    },
    {
      "confidence": 1,
      "game": {
        "author": "rlars",
        "name": "occupymoon_game",
        "release": 15950,
        "short_description": "Work in Progress. This game will send you to the moon!",
        "thumbnail": "https://content.luanti.org/thumbnails/1/2230ac18b9.png",
        "title": "Occupy Moon",
        "type": "game"
      },
      "supports": true
    },
    {
      "confidence": 1,
      "game": {
        "aliases": ["VanessaE/dreambuilder_game"],
        "author": "mt-mods",
        "name": "dreambuilder_game",
        "release": 32058,
        "short_description": "Dreambuilder is my attempt to give the player pretty much everything they could ever want to build with, and all the tools they should need to actually get the job done.",
        "thumbnail": "https://content.luanti.org/thumbnails/1/881d766d45.png",
        "title": "Dreambuilder Game",
        "type": "game"
      },
      "supports": true
    },
    {
      "confidence": 1,
      "game": {
        "author": "Big_Caballito",
        "name": "no_mans_land",
        "release": 8685,
        "short_description": "Work in Progress. Survive No Man's Land, where TNT rains from the sky, and destroys everything. This is a Work in Progress, I wanna add more features & lore",
        "thumbnail": "https://content.luanti.org/thumbnails/1/968d27792c.png",
        "title": "No Man's Land",
        "type": "game"
      },
      "supports": true
    },
    {
      "confidence": 1,
      "game": {
        "author": "Casimir",
        "name": "voxelgarden",
        "release": 32008,
        "short_description": "A classic game for exploring, survival and building. Maintained by rudzik8",
        "thumbnail": "https://content.luanti.org/thumbnails/1/d936c3fce1.png",
        "title": "Voxelgarden",
        "type": "game"
      },
      "supports": true
    },
    {
      "confidence": 1,
      "game": {
        "author": "bell07",
        "name": "whynot_game",
        "release": 31524,
        "short_description": "Aims to get all existing high quality mods working together",
        "thumbnail": "https://content.luanti.org/thumbnails/1/6f56447689.png",
        "title": "WhyNot?",
        "type": "game"
      },
      "supports": true
    },
    {
      "confidence": 1,
      "game": {
        "author": "Kimapr",
        "name": "nonsensical_skyblock",
        "release": 27427,
        "short_description": "skyblock game BASED on crafting. no quest cringe! bonemeal go brrrr",
        "thumbnail": "https://content.luanti.org/thumbnails/1/2f8309e348.png",
        "title": "Nonsensical Skyblock",
        "type": "game"
      },
      "supports": true
    },
    {
      "confidence": 1,
      "game": {
        "author": "1248",
        "name": "regnum2",
        "release": 28585,
        "short_description": "This is the second part of Regnum",
        "thumbnail": "https://content.luanti.org/thumbnails/1/Hmlddw7prL.png",
        "title": "Regnum 2",
        "type": "game"
      },
      "supports": true
    },
    {
      "confidence": 1,
      "game": {
        "author": "Amaz",
        "name": "lordofthetest",
        "release": 28811,
        "short_description": "LOTR-inspired subgame. Explore the world of Middle-Earth, the one subgame to rule them all!",
        "thumbnail": "https://content.luanti.org/thumbnails/1/d3872b989b.png",
        "title": "Lord of the Test",
        "type": "game"
      },
      "supports": true
    },
    {
      "confidence": 1,
      "game": {
        "author": "MeseCraft",
        "name": "mesecraft",
        "release": 30046,
        "short_description": "Work in Progress. The best game for Minetest. A survival game with new depth, mechanics, biomes, mobs and many essential additions. Has a focus on being fun, user-friendly, stable, and minimalist but featured.",
        "thumbnail": "https://content.luanti.org/thumbnails/1/bd43210a7e.png",
        "title": "MeseCraft",
        "type": "game"
      },
      "supports": true
    },
    {
      "confidence": 1,
      "game": {
        "author": "1248",
        "name": "regnum",
        "release": 31458,
        "short_description": "Fight monsters, collect XP, craft battleaxes, armor, guns and lots more.",
        "thumbnail": "https://content.luanti.org/thumbnails/1/3EqCRnJzzv.png",
        "title": "Regnum",
        "type": "game"
      },
      "supports": true
    },
    {
      "confidence": 1,
      "game": {
        "author": "jgordon510",
        "name": "gridlocks",
        "release": 28415,
        "short_description": "Learn programming, solve puzzles, and make pixelart.  An escape room game.",
        "thumbnail": "https://content.luanti.org/thumbnails/1/5cbe6a208b.png",
        "title": "gridlocks",
        "type": "game"
      },
      "supports": true
    },
    {
      "confidence": 1,
      "game": {
        "author": "1248",
        "name": "castrum",
        "release": 4788,
        "short_description": "You are on a floor plan of a castle. Collect resources and rebuild the old castle ",
        "thumbnail": "https://content.luanti.org/thumbnails/1/68ovEdgCu3.png",
        "title": "Castrum",
        "type": "game"
      },
      "supports": true
    },
    {
      "confidence": 1,
      "game": {
        "author": "JavaFXpert",
        "name": "qiskitblocks",
        "release": 5212,
        "short_description": "Teaching Quantum Computing using Qiskit in a block world",
        "thumbnail": "https://content.luanti.org/thumbnails/1/r9yczgJPla.png",
        "title": "QiskitBlocks",
        "type": "game"
      },
      "supports": true
    },
    {
      "confidence": 1,
      "game": {
        "author": "TheFanne",
        "name": "raining_nodes",
        "release": 1787,
        "short_description": "Survive in a strange world where nodes constantly rain down from the sky!",
        "thumbnail": "https://content.luanti.org/thumbnails/1/VgGn91cicQ.png",
        "title": "Raining Nodes",
        "type": "game"
      },
      "supports": true
    },
    {
      "confidence": 1,
      "game": {
        "author": "hilol",
        "name": "epic_combat",
        "release": 27975,
        "short_description": "Fight your enemies with various weapons and protect yourself with distinct sets of Armour, whilst sharpening your skills in PVP and PVE.",
        "thumbnail": "https://content.luanti.org/thumbnails/1/a0b633cedd.png",
        "title": "Epic Combat",
        "type": "game"
      },
      "supports": true
    },
    {
      "confidence": 1,
      "game": {
        "author": "Noodlemire",
        "name": "voxeldungeon",
        "release": 9212,
        "short_description": "This is a recreation and adaptation of an Android rogue-like game, Pixel Dungeon by Watabou.",
        "thumbnail": "https://content.luanti.org/thumbnails/1/80LJjnqDJn.png",
        "title": "Voxel Dungeon",
        "type": "game"
      },
      "supports": true
    },
    {
      "confidence": 1,
      "game": {
        "aliases": ["Minetest/minetest_game"],
        "author": "Luanti",
        "name": "minetest_game",
        "release": 31898,
        "short_description": "The classic \"Minetest\". A lightweight and well-maintained base for modding",
        "thumbnail": "https://content.luanti.org/thumbnails/1/8ffd1409ff.png",
        "title": "Minetest Game",
        "type": "game"
      },
      "supports": true
    },
    {
      "confidence": 1,
      "game": {
        "author": "EmptyStar",
        "name": "asuna",
        "release": 31816,
        "short_description": "A vibrant world of beautiful biomes. Explore, discover, create.",
        "thumbnail": "https://content.luanti.org/thumbnails/1/f334649d84.png",
        "title": "Asuna",
        "type": "game"
      },
      "supports": true
    }
  ],
  "issue_tracker": "https://github.com/nolombic/more_up_packs/issues/new/choose/",
  "license": "MIT",
  "long_description": "# more_up_packs \nUpgrade your upgrade packs so you can have even higher stats!  \nAffected stats are health and breath.  \n\n## Higher stats, whaaaa?\n[The original upgrade_packs mod by Krock](https://content.luanti.org/packages/Krock/upgrade_packs/ \"Link to the upgrade_packs minetest ContentDB site\") added four slots to the players inventory which they were able to fill with either +10 Health or +5 Breath each.  \nUsing only that mod a player could have up to +40HP or +20 Breath.  \nI however thought that this wouldn't be enough for **some** reason.  \n\n### So I've added more packs.\nIntroducing:  \n>#### +20HP  \n>#### +30HP  \n>#### +40HP  \n>#### +50HP  \n>as well as  \n>#### +10 Breath  \n>#### +15 Breath  \n>#### +20 Breath\n\n## That's all fine and dandy but how do you even craft them?\nIn order to craft one of these packs you take the previous level and surround it with the right items in order to upgrade the upgrade pack.\n\n### +10HP (from [the original upgrade_packs mod by Krock](https://content.luanti.org/packages/Krock/upgrade_packs/ \"Link to the upgrade_packs minetest ContentDB site\")) \n\n>To craft a +10HP upgrade pack, you'll need:  \n>4 copper ingots  \n>4 mese crystals  \n>1 glass bottle  \n>\n>#### Arrange it like this:\n>\n>>Put copper ingots into the four corners of the crafting grid. Put an empty glass bottle into the middle spot. Fill in the rest with mese crystals.  \n>\n>#### Unlocked award IF [awards](https://content.luanti.org/packages/rubenwardy/awards/ \"Link to the awards minetest ContentDB site\") is used:\n>\n>>**Rejuvination**  \n\n### +20HP  \n\n>To craft a +20HP upgrade pack, you'll need:  \n>4 gold ingots  \n>2 mese crystals  \n>2 obsidian shards  \n>1 +10HP upgrade pack\n>\n>#### Arrange it like this:\n>\n>>Put gold ingots into the four corners of the crafting grid. Put a +10HP upgrade pack into the middle spot. Place mese crystals above and below it. Fill in the sides with obsidian shards.  \n>\n>#### Unlocked award IF [awards](https://content.luanti.org/packages/rubenwardy/awards/ \"Link to the awards minetest ContentDB site\") is used:\n>\n>>**Prolonged Life**  \n\n###  +30HP  \n\n>To craft a +30HP upgrade pack, you'll need:  \n>4 diamonds  \n>2 mese crystals  \n>2 obsidian  \n>1 +20HP upgrade pack\n>\n>#### Arrange it like this:\n>\n>>Put diamonds into the four corners of the crafting grid. Put a +20HP upgrade pack into the middle spot. Place mese crystals into the slots above and below it. Fill in the sides with obsidian.  \n>\n>#### Unlocked award IF [awards](https://content.luanti.org/packages/rubenwardy/awards/ \"Link to the awards minetest ContentDB site\") is used:\n>\n>>**Fountain of Life**  \n\n### +40HP  \n\n>#### IF [mtg_plus](https://content.luanti.org/packages/Wuzzy/mtg_plus/ \"Link to the mtg_plus minetest ContentDB site\") is used\n>\n>>To craft a +40HP upgrade pack, you'll need:  \n>>4 diamond blocks  \n>>2 mese blocks  \n>>2 obsidian bricks  \n>>1 +30HP upgrade pack\n>>\n>>##### Arrange it like this:\n>>\n>>>Put diamond blocks into the four corners of the crafting grid. Put a +30HP upgrade pack into the middle spot. Place mese blocks above and below it. Fill in the sides with obsidian bricks.  \n>\n>#### IF [mtg_plus](https://content.luanti.org/packages/Wuzzy/mtg_plus/ \"Link to the mtg_plus minetest ContentDB site\") is NOT used\n>\n>>To craft a +40HP upgrade pack, you'll need:  \n>>4 diamond blocks  \n>>2 mese blocks  \n>>2 obsidian blocks  \n>>1 +30HP upgrade pack\n>>\n>>##### Arrange it like this:\n>>\n>>>Put diamond blocks into the four corners of the crafting grid. Put a +30HP upgrade pack into the middle spot. Place mese blocks above and below it. Fill in the sides with obsidian blocks.  \n>\n>#### Unlocked award IF [awards](https://content.luanti.org/packages/rubenwardy/awards/ \"Link to the awards minetest ContentDB site\") is used:\n>\n>>**Approaching Invincibility**  \n\n### +50HP  \n\n>#### IF [mtg_plus](https://content.luanti.org/packages/Wuzzy/mtg_plus/ \"Link to the mtg_plus minetest ContentDB site\") is used\n>\n>>To craft a +50HP upgrade pack, you'll need:  \n>>4 aggregated diamond blocks (from [the mtg_plus mod by Wuzzy](https://content.luanti.org/packages/Wuzzy/mtg_plus/ \"Link to the mtg_plus minetest ContentDB site\"))  \n>>2 mese blocks  \n>>2 gold-framed obsidian bricks (from [the mtg_plus mod by Wuzzy](https://content.luanti.org/packages/Wuzzy/mtg_plus/ \"Link to the mtg_plus minetest ContentDB site\"))  \n>>1 +40HP upgrade pack\n>>\n>>##### Arrange it like this:\n>>\n>>>Put aggregated diamond blocks into the four corners of the crafting grid. Put a +40HP upgrade pack into the middle spot. Place mese blocks above and below it. Fill in the sides with gold-framed obsidan bricks.  \n>\n>#### IF [mtg_plus](https://content.luanti.org/packages/Wuzzy/mtg_plus/ \"Link to the mtg_plus minetest ContentDB site\") is NOT used\n>\n>>To craft a +50HP upgrade pack, you'll need:  \n>>3 diamond blocks  \n>>3 mese blocks  \n>>2 obsidian bricks  \n>>1 +40HP upgrade pack\n>>\n>>##### Arrange it like this:\n>>\n>>>Put mese blocks into the top left and top right as well as the lower center of the crafting grid. Do the same with diamond blocks, but mirrored; lower left and right and upper center. Place a +40HP upgrade pack into the center. Fill in the rest with obsidian bricks.  \n>\n>#### Unlocked award IF [awards](https://content.luanti.org/packages/rubenwardy/awards/ \"Link to the awards minetest ContentDB site\") is used:\n>\n>>**Cheating Death**  \n\n### +5 Breath (from [the original upgrade_packs mod by Krock](https://content.luanti.org/packages/Krock/upgrade_packs/ \"Link to the upgrade_packs minetest ContentDB site\"))\n\n>To craft a +5 Breath upgrade pack, you'll need:  \n>4 tin ingots  \n>4 mese crystals  \n>1 steel bottle  \n>\n>#### Arrange it like this:\n>\n>>Put tin ingots into the four corners of the crafting grid. Put an empty steel bottle into the middle spot. Fill in the rest with mese crystals.  \n>\n>#### Unlocked award IF [awards](https://content.luanti.org/packages/rubenwardy/awards/ \"Link to the awards minetest ContentDB site\") is used:\n>\n>>**Breathing in Deeply**  \n\n### +10 Breath  \n\n>To craft a +10 Breath upgrade pack, you'll need:  \n>4 tin ingots  \n>4 mese crystals  \n>1 +5 Breath upgrade pack  \n>\n>#### Arrange it like this:\n>\n>>Put bronze ingots into the four corners of the crafting grid. Put a +5 Breath upgrade pack into the middle spot. Fill in the rest with mese crystals.  \n>\n>#### Unlocked award IF [awards](https://content.luanti.org/packages/rubenwardy/awards/ \"Link to the awards minetest ContentDB site\") is used:\n>\n>>**Becoming Amphibious**  \n\n### +15 Breath  \n\n>To craft a +15 Breath upgrade pack, you'll need:  \n>4 steel ingots  \n>2 mese crystals  \n>2 obsidian shards  \n>1 +10 Breath upgrade pack  \n>\n>#### Arrange it like this:\n>\n>>Put steel ingots into the four corners of the crafting grid. Put a +10 Breath upgrade pack into the middle spot. Place obsidian shards above and below it. Fill in the sides with mese crystals.  \n>\n>#### Unlocked award IF [awards](https://content.luanti.org/packages/rubenwardy/awards/ \"Link to the awards minetest ContentDB site\") is used:\n>\n>>**Growing Gills**  \n\n### +20 Breath  \n\n>To craft a +20 Breath upgrade pack, you'll need:  \n>4 obsidian shards  \n>2 mese crystals  \n>2 diamonds  \n>1 +15 Breath upgrade pack  \n>\n>#### Arrange it like this:\n>\n>>Put obsidian shards into the four corners of the crafting grid. Put a +15 Breath upgrade pack into the middle spot. Place diamonds aboe and below it. Fill in the sides with mese crystals.  \n>\n>#### Unlocked award IF [awards](https://content.luanti.org/packages/rubenwardy/awards/ \"Link to the awards minetest ContentDB site\") is used:\n>\n>>**Underwater Breathing**  \n\n## They're even translated into ***some*** languages\n\nTranslations currently cover these languages:\n\n### English ²\n### German ²\n### Dutch ¹ ² ³\n### French ¹ ⁵\n### Spanish ¹ ² ⁴\n\n¹ using [Deepl](https://deepl.com/translator)  \n² from previous knowledge like classes or culture  \n³ derived from similarities with other languages, e.g. German and Dutch  \n⁴ with outside help  \n⁵ pending proofreading  \n  \nA template for the translation can be found on the associated GitHub page.\n\n## Last but not least: Installation and dependencies\n\nInstallation of a mod must not be hard. Simply head into your minetest 5.0+ game and go to the ***Content*** tab. Tap on ***browse online content*** and wait for it to load up the available mod list. Using the search bar you have to make sure to install these mods:  \n  \n### [upgrade_packs](https://content.luanti.org/packages/Krock/upgrade_packs/ \"Link to the upgrade_packs minetest ContentDB site\")\nthe base that brings the core functionality. Must-have for this mod.  \n### [mtg_plus](https://content.luanti.org/packages/Wuzzy/mtg_plus/ \"Link to the mtg_plus minetest ContentDB site\")\noptionally used for the +50HP upgrade pack to make it harder to craft.  \n### [awards](https://content.luanti.org/packages/rubenwardy/awards/ \"Link to the awards minetest ContentDB site\")\nif you'd like to be rewarded by a popup for your efforts.\n### [more_up_packs](https://content.luanti.org/packages/nolombic/more_up_packs/)\nthis mod.  \n\n### Make sure the mods are enabled on your world! Otherwise they won't do anything but sit around unused.\n\nAlternatively download the individual mods from their respective pages, extract their .zip files, maybe rename them accordingly, and move them to your mods folder.\n\n## Thank you for showing interest in my silly little mod\nYours sincerely,  \nnolombic\n",
  "maintainers": ["nolombic"],
  "media_license": "MIT",
  "name": "more_up_packs",
  "provides": ["more_up_packs"],
  "release": 4743,
  "repo": "https://github.com/nolombic/more_up_packs",
  "score": 10.3,
  "screenshots": ["https://content.luanti.org/uploads/d6KxN5NjGj.png"],
  "short_description": "Upgrade your upgrade packs so you can have even higher stats!",
  "state": "APPROVED",
  "tags": ["player_effects", "survival"],
  "thumbnail": "https://content.luanti.org/thumbnails/1/d6KxN5NjGj.png",
  "title": "More Upgrade Packs",
  "translation_url": null,
  "type": "mod",
  "url": "https://content.luanti.org/packages/nolombic/more_up_packs/releases/4743/download/",
  "video_thumbnail_url": null,
  "video_url": null,
  "website": null,
  "dependencies": {
    "Krock/upgrade_packs": [
      {
        "is_optional": false,
        "name": "vessels",
        "packages": [
          "1248/regnum",
          "bell07/whynot_game",
          "Noodlemire/voxeldungeon",
          "sunnysideup/holidayhorrors",
          "rubenwardy/capturetheflag",
          "Amaz/lordofthetest",
          "1248/castrum",
          "NotaB/tolkientest",
          "EmptyStar/asuna",
          "MeseCraft/mesecraft",
          "miroptics/qiskitblocks_miro",
          "Kimapr/nonsensical_skyblock",
          "Replicat/wyrm_cube",
          "JavaFXpert/qiskitblocks",
          "jgordon510/gridlocks",
          "Big_Caballito/no_mans_land",
          "Casimir/voxelgarden",
          "TheFanne/raining_nodes",
          "rlars/occupymoon_game",
          "PetiAPocok/minetest_extended",
          "mt-mods/dreambuilder_game",
          "hilol/epic_combat",
          "jara25/yams",
          "Luanti/minetest_game"
        ]
      },
      {
        "is_optional": false,
        "name": "default",
        "packages": [
          "1248/regnum",
          "Hi_World/newplanet",
          "Noodlemire/voxeldungeon",
          "NotaB/tolkientest",
          "JALdMIC/survivethedays",
          "sunnysideup/holidayhorrors",
          "BuckarooBanzay/mesecons_lab",
          "nam/porko",
          "bell07/whynot_game",
          "rubenwardy/capturetheflag",
          "Amaz/lordofthetest",
          "1248/castrum",
          "AiTechEye/xaenvironment",
          "EmptyStar/asuna",
          "debiankaios/proxima_survival",
          "carlos_rupp/berzerkpt",
          "MeseCraft/mesecraft",
          "miroptics/qiskitblocks_miro",
          "KareaGhandTrail/block_assault_mapmaker",
          "Thunder1035/etb",
          "KareaGhandTrail/block_assault",
          "Replicat/wyrm_cube",
          "JavaFXpert/qiskitblocks",
          "Kimapr/nonsensical_skyblock",
          "jgordon510/gridlocks",
          "giga-turbo/codecube",
          "niwla23/runorfall",
          "Thunder1035/pacman",
          "Big_Caballito/no_mans_land",
          "hilol/epic_combat",
          "TheFanne/raining_nodes",
          "rlars/occupymoon_game",
          "Casimir/voxelgarden",
          "PetiAPocok/minetest_extended",
          "mooD_Slayer/ksurvive",
          "jara25/yams",
          "mt-mods/dreambuilder_game",
          "Luanti/minetest_game"
        ]
      }
    ],
    "nolombic/more_up_packs": [
      {
        "is_optional": false,
        "name": "default",
        "packages": [
          "1248/regnum",
          "Hi_World/newplanet",
          "Noodlemire/voxeldungeon",
          "NotaB/tolkientest",
          "JALdMIC/survivethedays",
          "sunnysideup/holidayhorrors",
          "BuckarooBanzay/mesecons_lab",
          "nam/porko",
          "bell07/whynot_game",
          "rubenwardy/capturetheflag",
          "Amaz/lordofthetest",
          "1248/castrum",
          "AiTechEye/xaenvironment",
          "EmptyStar/asuna",
          "debiankaios/proxima_survival",
          "carlos_rupp/berzerkpt",
          "MeseCraft/mesecraft",
          "miroptics/qiskitblocks_miro",
          "KareaGhandTrail/block_assault_mapmaker",
          "Thunder1035/etb",
          "KareaGhandTrail/block_assault",
          "Replicat/wyrm_cube",
          "JavaFXpert/qiskitblocks",
          "Kimapr/nonsensical_skyblock",
          "jgordon510/gridlocks",
          "giga-turbo/codecube",
          "niwla23/runorfall",
          "Thunder1035/pacman",
          "Big_Caballito/no_mans_land",
          "hilol/epic_combat",
          "TheFanne/raining_nodes",
          "rlars/occupymoon_game",
          "Casimir/voxelgarden",
          "PetiAPocok/minetest_extended",
          "mooD_Slayer/ksurvive",
          "jara25/yams",
          "mt-mods/dreambuilder_game",
          "Luanti/minetest_game"
        ]
      },
      {
        "is_optional": false,
        "name": "upgrade_packs",
        "packages": ["Krock/upgrade_packs"]
      }
    ]
  },
  "hash": "0hnq7h0qfaqgsnksb607mai0kmhbrjhqkpb1rx09swh1xsb65y5l"
}
