{"author":"rubenwardy","content_warnings":[],"created_at":"2018-06-20T15:52:06.758372","dev_state":"MAINTENANCE_ONLY","donate_url":"https://rubenwardy.com/donate/","downloads":1839,"forum_url":null,"forums":null,"game_support":[],"issue_tracker":"https://github.com/rubenwardy/vote_kick/issues/new/choose/","license":"LGPL-2.1-only","long_description":"","maintainers":["rubenwardy"],"media_license":"LGPL-2.1-only","name":"vote_kick","provides":["vote_kick"],"release":289,"repo":"https://github.com/rubenwardy/vote_kick","score":4.2,"screenshots":["https://content.luanti.org/uploads/35050153d8.png"],"short_description":"Adds kick voting using the vote API","state":"APPROVED","tags":["multiplayer","server_tools"],"thumbnail":"https://content.luanti.org/thumbnails/1/35050153d8.png","title":"Kick Vote","translation_url":null,"type":"mod","url":"https://content.luanti.org/packages/rubenwardy/vote_kick/releases/289/download/","video_thumbnail_url":null,"video_url":null,"website":null,"dependencies":{"rubenwardy/vote":[],"rubenwardy/vote_kick":[{"is_optional":false,"name":"vote","packages":["rubenwardy/vote"]}]},"hash":"0hi7dgibfxvpii128yhv28kc8sb7kwvpadmgzlli1rvkxvkns48h"}