{"author":"kestral","content_warnings":[],"created_at":"2019-03-17T21:17:28.141686","dev_state":null,"donate_url":null,"downloads":4384,"forum_url":"https://forum.luanti.org/viewtopic.php?t=23308","forums":23308,"game_support":[{"confidence":11,"game":{"author":"Minetest","name":"minetest_game","release":29742,"short_description":"The classic \"Minetest\". A lightweight and well-maintained base for modding","thumbnail":"https://content.luanti.org/thumbnails/1/8ffd1409ff.png","title":"Minetest Game","type":"game"},"supports":true}],"issue_tracker":"https://github.com/kestral246/default_grid/issues/new/choose/","license":"CC-BY-3.0","long_description":"Adds a grid overlay to the Minetest Game 5.0 default textures.\n\nThis texture pack provides grid overlay textures, which are placed over the existing default textures from Minetest Game 5.0. This is done without needing to copy the default textures, by using the power of override.txt mapping file.\n\nIt places the grid over regular nodes like ground and ground cover, stones (including block and brick variants), metal blocks, woods (planks only), and all 37 flavors of stairs variants.\n\nNote however that it intentionally doesn't place a grid over trees, plants, liquids, tools, and irregular shapes like fences and ladders. These will still remain the same as default.\n\nAlso note that the overlays are drawn at 32px for a finer grid. This means that all the gridded default textures will be scaled to 32px, even though they'll still look like they're 16px.\n\n\n**It's also possible to place a grid over most other texture packs.**\n\nTo do this, it's necessary to place a copy of (or link to) the other texture pack in the default_grid directory, and select default_grid as the texture to use.\n\nNote that the grid will still only be applied to the default, farming, stairs, and wool nodes currently supported by default_grid.\n\nThis works because default_grid doesn't actually supply any default_* textures—it just used the system ones. However, any textures placed in the default_grid directory will override the system ones. Minetest will also autoscale to the largest texture, so resolution of texture packs shouldn't matter either. However, I wouldn't try putting in more than one other texture pack there at the same time.","maintainers":["kestral"],"media_license":"CC-BY-3.0","name":"default_grid","provides":[],"release":1999,"repo":"https://github.com/kestral246/default_grid","score":12.5,"screenshots":["https://content.luanti.org/uploads/lr2cpyUcrO.png","https://content.luanti.org/uploads/C5pV0SjV6P.png"],"short_description":"Add grid overlay to MT Game 5.0 default textures.","state":"APPROVED","tags":["32px"],"thumbnail":"https://content.luanti.org/thumbnails/1/lr2cpyUcrO.png","title":"Default Grid","translation_url":null,"type":"txp","url":"https://content.luanti.org/packages/kestral/default_grid/releases/1999/download/","video_thumbnail_url":null,"video_url":null,"website":null,"dependencies":{"kestral/default_grid":[]},"hash":"05ns6bj0lnkfa92f4qy6qlllvg7b54warfkj2b5rd4ibry2fi0x8"}