{"author":"mt-mods","content_warnings":[],"created_at":"2018-05-24T16:31:12.156601","dev_state":null,"donate_url":null,"downloads":55864,"forum_url":"https://forum.luanti.org/viewtopic.php?t=12999","forums":12999,"game_support":[],"issue_tracker":"https://gitlab.com/VanessaE/biome_lib/issues","license":"LGPL-3.0-only","long_description":"The biome spawning and management library for Plantlife","maintainers":["VanessaE","mt-mods"],"media_license":"CC-BY-SA-4.0","name":"biome_lib","provides":["biome_lib"],"release":23471,"repo":"https://github.com/mt-mods/biome_lib","score":280.5,"screenshots":["https://content.luanti.org/uploads/4f5975c1b0.png"],"short_description":"The biome spawning and management library.","state":"APPROVED","tags":["environment","mapgen"],"thumbnail":"https://content.luanti.org/thumbnails/1/4f5975c1b0.png","title":"Biome Lib","translation_url":null,"type":"mod","url":"https://content.luanti.org/packages/mt-mods/biome_lib/releases/23471/download/","video_thumbnail_url":null,"video_url":null,"website":null,"dependencies":{"mt-mods/biome_lib":[]},"hash":"167qvarralh3g84cf6gi010lvmagg6yh19a4f4j0dh6vhb8c099z"}